discord/ext/music/__init__.py
discord/ext/music/player.py
discord/ext/music/playlist.py
discord/ext/music/track.py
discord/ext/music/voice_client.py
discord/ext/music/equalizer/__init__.py
discord/ext/music/equalizer/base.py
discord/ext/music/equalizer/pydub.py
discord/ext/music/opus_encoder/__init__.py
discord/ext/music/opus_encoder/av.py
discord/ext/music/utils/__init__.py
discord/ext/music/utils/errors.py
discord/ext/music/utils/var.py
discord/ext/music/voice_source/__init__.py
discord/ext/music/voice_source/legacy.py
discord/ext/music/voice_source/miniaudio.py
discord/ext/music/voice_source/av/__init__.py
discord/ext/music/voice_source/av/audio_source.py
discord/ext/music/voice_source/av/io.py
discord/ext/music/voice_source/av/stream.py
discord_ext_music-0.3.0.dist-info/LICENSE
discord_ext_music-0.3.0.dist-info/METADATA
discord_ext_music-0.3.0.dist-info/WHEEL
discord_ext_music-0.3.0.dist-info/top_level.txt
discord_ext_music-0.3.0.dist-info/RECORD
