Metadata-Version: 2.1
Name: discord-ext-music
Version: 0.3.0
Summary: An easy-to-use music extension for discord.py
Home-page: https://github.com/mansuf/discord-ext-music
Author: Rahman Yusuf
Author-email: danipart4@gmail.com
License: MIT
Platform: UNKNOWN
Classifier: Development Status :: 5 - Production/Stable
Classifier: Intended Audience :: Developers
Classifier: License :: OSI Approved :: MIT License
Classifier: Programming Language :: Python :: 3.8
Classifier: Programming Language :: Python :: 3.9
Classifier: Topic :: Software Development :: Libraries :: Python Modules
Classifier: Topic :: Multimedia :: Sound/Audio
Requires-Python: >=3.8
License-File: LICENSE
Requires-Dist: discord.py[voice]
Provides-Extra: all
Requires-Dist: pydub ; extra == 'all'
Requires-Dist: scipy ; extra == 'all'
Requires-Dist: miniaudio ; extra == 'all'
Requires-Dist: av ; extra == 'all'
Provides-Extra: av
Requires-Dist: av (==8.0.3) ; extra == 'av'
Provides-Extra: docs
Requires-Dist: sphinx ; extra == 'docs'
Requires-Dist: furo ; extra == 'docs'
Provides-Extra: equalizer
Requires-Dist: pydub ; extra == 'equalizer'
Requires-Dist: scipy ; extra == 'equalizer'
Provides-Extra: miniaudio
Requires-Dist: miniaudio ; extra == 'miniaudio'
